{
    "name": "gamePad",
    "version": "1.0.0",
    "description": "This library is DFRobot gamer:bit provides the game handle control function.",
    "license": "GNU",
    "dependencies": {
        "core": "*",
        "radio": "*"
    },
    "files": [
        "README.md",
        "gamerpad.cpp",
        "main.ts",
        "_locales/zh/gamePad-strings.json"
    ],
    "testFiles": [
        "test.ts"
    ],
    "public": false,
    "supportedTargets": [
        "microbit"
    ],
    "preferredEditor": "tsprj"
}
